sectionproperties/__init__.py
sectionproperties/py.typed
sectionproperties/analysis/__init__.py
sectionproperties/analysis/fea.py
sectionproperties/analysis/plastic_section.py
sectionproperties/analysis/section.py
sectionproperties/analysis/solver.py
sectionproperties/post/__init__.py
sectionproperties/post/fibre.py
sectionproperties/post/post.py
sectionproperties/post/stress_post.py
sectionproperties/pre/__init__.py
sectionproperties/pre/bisect_section.py
sectionproperties/pre/geometry.py
sectionproperties/pre/pre.py
sectionproperties/pre/rhino.py
sectionproperties/pre/library/__init__.py
sectionproperties/pre/library/bridge_sections.py
sectionproperties/pre/library/concrete_sections.py
sectionproperties/pre/library/nastran_sections.py
sectionproperties/pre/library/primitive_sections.py
sectionproperties/pre/library/steel_sections.py
sectionproperties/pre/library/utils.py
sectionproperties-3.8.0.dist-info/METADATA
sectionproperties-3.8.0.dist-info/WHEEL
sectionproperties-3.8.0.dist-info/licenses/LICENSE
sectionproperties-3.8.0.dist-info/RECORD
