Metadata-Version: 2.4
Name: sectionproperties
Version: 3.8.0
Summary: A python package for the analysis of arbitrary cross-sections using the finite element method.
Project-URL: Homepage, https://sectionproperties.readthedocs.io
Project-URL: Documentation, https://sectionproperties.readthedocs.io
Project-URL: Repository, https://github.com/robbievanleeuwen/section-properties
Project-URL: Issues, https://github.com/robbievanleeuwen/section-properties/issues
Project-URL: Changelog, https://github.com/robbievanleeuwen/section-properties/releases
Author-email: Robbie van Leeuwen <robbie.vanleeuwen@gmail.com>
Maintainer-email: Robbie van Leeuwen <robbie.vanleeuwen@gmail.com>, Connor Ferster <connorferster@gmail.comm>
License: MIT License
License-File: LICENSE
Keywords: computational-mechanics,cross-section,finite-element-analysis,structural-engineering
Classifier: Development Status :: 5 - Production/Stable
Classifier: Environment :: Console
Classifier: License :: OSI Approved :: MIT License
Classifier: Natural Language :: English
Classifier: Programming Language :: Python :: 3.11
Classifier: Programming Language :: Python :: 3.12
Classifier: Programming Language :: Python :: 3.13
Classifier: Topic :: Scientific/Engineering
Requires-Python: <3.14,>=3.11
Requires-Dist: cytriangle>=2.0.0
Requires-Dist: matplotlib>=3.9.2
Requires-Dist: more-itertools>=10.5.0
Requires-Dist: numpy>=1.26.4
Requires-Dist: rich[jupyter]>=13.9.4
Requires-Dist: scipy>=1.14.1
Requires-Dist: shapely>=2.0.7
Provides-Extra: dxf
Requires-Dist: cad-to-shapely>=0.3.2; extra == 'dxf'
Provides-Extra: numba
Requires-Dist: numba>=0.60.0; extra == 'numba'
Provides-Extra: pardiso
Requires-Dist: pypardiso>=0.4.6; (platform_system == 'Windows' or platform_system == 'Linux') and extra == 'pardiso'
Provides-Extra: rhino
Requires-Dist: rhino-shapley-interop>=0.0.4; extra == 'rhino'
Requires-Dist: rhino3dm==8.17.0b0; extra == 'rhino'
